pymotyc/__init__.py
pymotyc/collection.py
pymotyc/database.py
pymotyc/engine.py
pymotyc/errors.py
pymotyc/model.py
pymotyc/query.py
pymotyc/util.py
pymotyc-0.9.0.dist-info/LICENSE
pymotyc-0.9.0.dist-info/METADATA
pymotyc-0.9.0.dist-info/WHEEL
pymotyc-0.9.0.dist-info/top_level.txt
pymotyc-0.9.0.dist-info/RECORD
