Metadata-Version: 2.1
Name: pymotyc
Version: 0.9.0
Summary: Statically typed asynchronous MongoDB collections with Pydantic models and Motor engine.
Home-page: https://github.com/AntonOvsyannikov/pymotyc
Author: Anton Ovsyannikov
Author-email: anton.ovsyannikov@gmail.com
License: MIT
Project-URL: Bug Tracker, https://github.com/AntonOvsyannikov/pymotyc/issues
Platform: UNKNOWN
Classifier: Programming Language :: Python :: 3
Classifier: License :: OSI Approved :: MIT License
Classifier: Operating System :: OS Independent
Classifier: Framework :: AsyncIO
Classifier: Development Status :: 4 - Beta
Requires-Python: >=3.7
Requires-Dist: pydantic (>=1.7)
Requires-Dist: motor (>=2.4)
Requires-Dist: typing-inspect (>=0.6)
